{
  "mcpServers": {
    "mcp-google-ads": {
      "command": "npx",
      "args": ["-y", "@weppa-cloud/mcp-google-ads"],
      "env": {
        "GOOGLE_ADS_DEVELOPER_TOKEN": "${GOOGLE_ADS_DEVELOPER_TOKEN}",
        "GOOGLE_ADS_CLIENT_ID": "${GOOGLE_ADS_CLIENT_ID}",
        "GOOGLE_ADS_CLIENT_SECRET": "${GOOGLE_ADS_CLIENT_SECRET}",
        "GOOGLE_ADS_REFRESH_TOKEN": "${GOOGLE_ADS_REFRESH_TOKEN}",
        "GOOGLE_ADS_CUSTOMER_ID": "${GOOGLE_ADS_CUSTOMER_ID}",
        "GOOGLE_ADS_LOGIN_CUSTOMER_ID": "${GOOGLE_ADS_CUSTOMER_ID}"
      }
    }
  }
}
